encryptcode/__init__.py
encryptcode/encryptcode.py
encryptcode/encryptit.sh
encryptcode/setup.py
encryptcode-0.1.0.dist-info/METADATA
encryptcode-0.1.0.dist-info/WHEEL
encryptcode-0.1.0.dist-info/top_level.txt
encryptcode-0.1.0.dist-info/RECORD
