Metadata-Version: 2.4
Name: encryptcode
Version: 0.1.0
Summary: Encryptcode tool to encrypt python files
Author-email: Mohammed Magar <mfmagar@gmail.com>
License: MIT
Requires-Python: >=3.8
Requires-Dist: cryptography>=45.0.7
Requires-Dist: cython>=3.1.3
Requires-Dist: python-dateutil>=2.9.0.post0
Requires-Dist: setuptools>=80.9.0
Requires-Dist: wheel>=0.45.1
